idem_azure/conf.py
idem_azure/version.py
idem_azure/acct/azure/login.py
idem_azure/acct/azure/mock.py
idem_azure/acct/metadata/azure.py
idem_azure/backup/virtual_networks/nat_gateways.py
idem_azure/backup/virtual_networks/public_ip_addresses.py
idem_azure/backup/virtual_networks/routes.py
idem_azure/exec/azure/init.py
idem_azure/exec/azure/permission.py
idem_azure/exec/azure/authorization/role_assignments.py
idem_azure/exec/azure/authorization/role_definitions.py
idem_azure/exec/azure/compute/disks.py
idem_azure/exec/azure/compute/log_analytics_workspace.py
idem_azure/exec/azure/compute/virtual_machines.py
idem_azure/exec/azure/key_vault/vault.py
idem_azure/exec/azure/management_groups/management_groups.py
idem_azure/exec/azure/network/firewall.py
idem_azure/exec/azure/network/firewall_policies.py
idem_azure/exec/azure/network/network_interfaces.py
idem_azure/exec/azure/network/network_security_groups.py
idem_azure/exec/azure/network/public_ip_addresses.py
idem_azure/exec/azure/network/route_tables.py
idem_azure/exec/azure/network/routes.py
idem_azure/exec/azure/network/security_rules.py
idem_azure/exec/azure/network/subnets.py
idem_azure/exec/azure/network/virtual_network_peerings.py
idem_azure/exec/azure/network/virtual_networks.py
idem_azure/exec/azure/policy/policy_assignments.py
idem_azure/exec/azure/policy/policy_definitions.py
idem_azure/exec/azure/resource_management/resource_groups.py
idem_azure/exec/azure/sql_database/databases.py
idem_azure/exec/azure/storage_resource_provider/storage_accounts.py
idem_azure/exec/azure/storage_resource_provider/storage_blob.py
idem_azure/exec/azure/subscription/attach_subscriptions.py
idem_azure/exec/azure/subscription/subscriptions.py
idem_azure/pop_create/azure/api_reference.py
idem_azure/pop_create/azure/api_spec.py
idem_azure/pop_create/azure/init.py
idem_azure/pop_create/azure/plugin.py
idem_azure/pop_create/azure/resource.py
idem_azure/pop_create/azure/rest.py
idem_azure/pop_create/azure/template.py
idem_azure-2.5.0.dist-info/LICENSE
idem_azure-2.5.0.dist-info/METADATA
idem_azure-2.5.0.dist-info/WHEEL
idem_azure-2.5.0.dist-info/top_level.txt
idem_azure-2.5.0.dist-info/RECORD
